bliss/__init__.py
bliss/cryogenicps.py
bliss/py.typed
bliss/release.py
bliss/setup_globals.py
bliss/beacon/__init__.py
bliss/beacon/beacon_api.py
bliss/beacon/beacon_server.py
bliss/beacon/protocol.py
bliss/beacon/app/__init__.py
bliss/beacon/app/app_dispatcher.py
bliss/beacon/app/beacon_server.py
bliss/beacon/redis/__init__.py
bliss/beacon/redis/redis.conf
bliss/beacon/redis/redis_data.conf
bliss/beacon/services/__init__.py
bliss/beacon/services/log_server.py
bliss/beacon/services/configuration/__init__.py
bliss/beacon/services/configuration/config_app.py
bliss/beacon/services/configuration/plugins/P201.html
bliss/beacon/services/configuration/plugins/__init__.py
bliss/beacon/services/configuration/plugins/_ct2.py
bliss/beacon/services/configuration/plugins/beamline.html
bliss/beacon/services/configuration/plugins/beamline.py
bliss/beacon/services/configuration/plugins/ct2.html
bliss/beacon/services/configuration/plugins/ct2.py
bliss/beacon/services/configuration/plugins/emotion.py
bliss/beacon/services/configuration/plugins/emotion_IcePAP.html
bliss/beacon/services/configuration/plugins/emotion_IcePAP_axis.html
bliss/beacon/services/configuration/plugins/emotion_axis.html
bliss/beacon/services/configuration/plugins/emotion_controller.html
bliss/beacon/services/configuration/plugins/session.html
bliss/beacon/services/configuration/plugins/session.py
bliss/beacon/services/configuration/static/css/beacon.css
bliss/beacon/services/configuration/static/css/bootstrap-notify.css
bliss/beacon/services/configuration/static/css/bootstrap-treeview.min.css
bliss/beacon/services/configuration/static/css/layout-default.min.css
bliss/beacon/services/configuration/static/css/bootstrap-notify-styles/alert-bangtidy.css
bliss/beacon/services/configuration/static/css/bootstrap-notify-styles/alert-blackgloss.css
bliss/beacon/services/configuration/static/js/beacon-utils.js
bliss/beacon/services/configuration/static/js/bootstrap-notify.js
bliss-2.3.0.dist-info/METADATA
bliss-2.3.0.dist-info/WHEEL
bliss-2.3.0.dist-info/entry_points.txt
bliss-2.3.0.dist-info/top_level.txt
bliss-2.3.0.dist-info/RECORD
