Metadata-Version: 2.4
Name: bliss
Version: 2.3.0
Summary: BeamLine Instrumentation Support Software
Author: BCU (ESRF)
Maintainer-email: bliss developers <bliss@esrf.fr>
License-Expression: LGPL-3.0-or-later
Project-URL: Homepage, https://gitlab.esrf.fr/bliss/bliss
Project-URL: Documentation, https://bliss.gitlab-pages.esrf.fr/bliss
Project-URL: Tracker, https://gitlab.esrf.fr/bliss/bliss/issues
Classifier: Intended Audience :: Science/Research
Classifier: Programming Language :: Python :: 3
Requires-Python: >=3.10
Requires-Dist: appdirs<1.5
Requires-Dist: beartype<0.23,>=0.17
Requires-Dist: blissdata-lima2~=2.0
Requires-Dist: blissdata<2.4,>=2.3
Requires-Dist: blisswriter<1.1,>=1.0.0
Requires-Dist: cerberus<1.4
Requires-Dist: cffi<2.1
Requires-Dist: docopt<0.7
Requires-Dist: esrf-ontologies<1.3,>=1
Requires-Dist: fabio<2025.11,>=0.12
Requires-Dist: flask<3.2,>=2.0.1
Requires-Dist: gevent<25,>=20.9.0
Requires-Dist: glom<24.12
Requires-Dist: greenlet<3.4,>=0.4.17
Requires-Dist: h5py!=3.3,!=3.4,<3.16,>=2.9
Requires-Dist: hdf5plugin<6.1
Requires-Dist: hiredis<3.4
Requires-Dist: lima2-client~=4.1
Requires-Dist: louie<2.1,>=2.0
Requires-Dist: lru-dict<1.5
Requires-Dist: matplotlib==3.9.*
Requires-Dist: mendeleev<0.16.0
Requires-Dist: mock<5.3
Requires-Dist: msgpack-numpy<0.5,>=0.4.4.2
Requires-Dist: msgpack<1.2
Requires-Dist: networkx<3.7,>2.4
Requires-Dist: numexpr<2.15
Requires-Dist: numpy<2,>=1.21.1
Requires-Dist: packaging<26
Requires-Dist: pandas<2.4
Requires-Dist: pathvalidate<3.4
Requires-Dist: pillow<12.1
Requires-Dist: pint<0.26
Requires-Dist: prompt-toolkit<3.1,>=3.0.50
Requires-Dist: psutil<7.2
Requires-Dist: ptpython<3.0.24,>=3.0.23
Requires-Dist: pygments<2.19.0
Requires-Dist: pyicat-plus<0.13,>=0.9.0
Requires-Dist: pyqt5<5.16,>=5.12
Requires-Dist: pyserial<3.6,>2
Requires-Dist: pytango<10.0,>9.4
Requires-Dist: querypool<1.2
Requires-Dist: redis<5.0.1,>=4
Requires-Dist: requests<2.33
Requires-Dist: resyst-client<0.19,>=0.18
Requires-Dist: ruamel.yaml<0.19
Requires-Dist: scipy<1.17,>=1.1.0
Requires-Dist: silx<2.3,~=2.2.0
Requires-Dist: simple-pid<2.1
Requires-Dist: sortedcontainers<2.5
Requires-Dist: tabulate<0.10
Requires-Dist: tblib<3.3,>=1.7
Requires-Dist: treelib<1.6,<=1.5.5
Requires-Dist: typing_extensions<4.16
Requires-Dist: xcalibu==1.0.1
Requires-Dist: yappi<1.8
Provides-Extra: dev
Requires-Dist: black==22.3; extra == "dev"
Requires-Dist: flake8; extra == "dev"
Requires-Dist: flake8-pep585; extra == "dev"
Requires-Dist: pre-commit; extra == "dev"
Requires-Dist: pytest-cov; extra == "dev"
Requires-Dist: pytest-mock; extra == "dev"
Requires-Dist: pytest-profiling!=1.8.0; extra == "dev"
Requires-Dist: pytest-rerunfailures; extra == "dev"
Requires-Dist: pytest-xvfb; extra == "dev"
Requires-Dist: pytest; extra == "dev"
Requires-Dist: scriv>=1.3.1; extra == "dev"
Requires-Dist: nosqltangodb==1.0.6; extra == "dev"
Requires-Dist: python-socketio[asyncio_client]; extra == "dev"
Provides-Extra: rest
Requires-Dist: pydantic; extra == "rest"
Requires-Dist: eval_type_backport; python_version == "3.9" and extra == "rest"
Requires-Dist: flask-socketio; extra == "rest"
Requires-Dist: flask; extra == "rest"
Requires-Dist: flask-cors; extra == "rest"
Requires-Dist: flask-openapi3; extra == "rest"
Provides-Extra: pymca
Requires-Dist: pymca>=5.8.1; extra == "pymca"
Provides-Extra: doc
Requires-Dist: markdown<3.4,>=3.2; extra == "doc"
Requires-Dist: mike; extra == "doc"
Requires-Dist: mkdocs-material>=8.2.11; extra == "doc"
Requires-Dist: mkdocs-material-extensions>=1.0.3; extra == "doc"
Requires-Dist: sphinx; extra == "doc"
